metsuperq/__init__.py
metsuperq/py.typed
metsuperq/analysis/__init__.py
metsuperq/analysis/base_analysis.py
metsuperq/analysis/constants.py
metsuperq/analysis/physics_validation.py
metsuperq/analysis/utils.py
metsuperq/data_handling/__init__.py
metsuperq/data_handling/hdf5_data_manager.py
metsuperq/data_handling/npl_converter.py
metsuperq/database/__init__.py
metsuperq/database/client.py
metsuperq/database/config.py
metsuperq/database/exceptions.py
metsuperq/database/schema.py
metsuperq/database/writer.py
metsuperq/integrations/__init__.py
metsuperq/integrations/measurement_processor.py
metsuperq/integrations/measurement_recorder.py
metsuperq/monitoring/__init__.py
metsuperq/monitoring/health.py
metsuperq/utils/__init__.py
metsuperq/utils/utils.py
metsuperq-0.1.0.dist-info/licenses/LICENSE
metsuperq-0.1.0.dist-info/METADATA
metsuperq-0.1.0.dist-info/WHEEL
metsuperq-0.1.0.dist-info/top_level.txt
metsuperq-0.1.0.dist-info/RECORD
