Metadata-Version: 2.4
Name: metsuperq
Version: 0.1.0
Summary: A project to define standards for analysis functions of experimental data in the MetSuperQ project.
Author-email: Orange Quantum Systems <info@orangeqs.com>
License-Expression: BSD-3-Clause
Project-URL: Homepage, https://opensource.orangeqs.info/metsuperq/
Keywords: metsuperq,quantum,analysis,data,standards
Classifier: Development Status :: 3 - Alpha
Classifier: Intended Audience :: Developers
Classifier: Intended Audience :: Science/Research
Classifier: Natural Language :: English
Classifier: Programming Language :: Python :: 3.11
Classifier: Programming Language :: Python :: 3.12
Classifier: Programming Language :: Python :: 3.13
Classifier: Programming Language :: Python :: 3.14
Classifier: Topic :: Scientific/Engineering :: Physics
Requires-Python: >=3.11
License-File: LICENSE
Requires-Dist: h5py>=3.12
Requires-Dist: lmfit>=1.3
Requires-Dist: matplotlib>=3.10
Requires-Dist: numpy>=2.1
Requires-Dist: qcodes>=0.50
Requires-Dist: scipy>=1.14
Requires-Dist: influxdb-client>=1.40
Requires-Dist: pydantic>=2.10
Requires-Dist: pydantic-settings>=2.6
Requires-Dist: psutil>=6.0
Dynamic: license-file
